README.rst
setup.cfg
setup.py
twitterbot_utils/TwiAuth.py
twitterbot_utils/TwiUtils.py
twitterbot_utils/Twibot.py
twitterbot_utils/__init__.py
twitterbot_utils.egg-info/PKG-INFO
twitterbot_utils.egg-info/SOURCES.txt
twitterbot_utils.egg-info/dependency_links.txt
twitterbot_utils.egg-info/requires.txt
twitterbot_utils.egg-info/top_level.txt