Metadata-Version: 1.1
Name: twitterbot-utils
Version: 0.0.9
Summary: wrapper around the Tweepy
Home-page: https://github.com/strizhechenko/twitterbot_utils
Author: Oleg Strizhechenko
Author-email: oleg.strizhechenko@gmail.com
License: GPL
Keywords: twitter api bot
Platform: UNKNOWN
Classifier: Development Status :: 3 - Alpha
Classifier: Intended Audience :: Developers
Classifier: Operating System :: MacOS
Classifier: Operating System :: POSIX
Classifier: Programming Language :: Python
Classifier: Programming Language :: Python :: 2
Classifier: Topic :: Software Development
Classifier: Topic :: Utilities
